README.rst
discovery.zip
screenshot.png
setup.py
docs/HISTORY.txt
docs/INSTALL.txt
docs/LICENSE.GPL
docs/LICENSE.txt
plonetheme/__init__.py
plonetheme.discovery.egg-info/PKG-INFO
plonetheme.discovery.egg-info/SOURCES.txt
plonetheme.discovery.egg-info/dependency_links.txt
plonetheme.discovery.egg-info/entry_points.txt
plonetheme.discovery.egg-info/namespace_packages.txt
plonetheme.discovery.egg-info/requires.txt
plonetheme.discovery.egg-info/top_level.txt
plonetheme/discovery/__init__.py
plonetheme/discovery/configure.zcml
plonetheme/discovery/profiles/default/metadata.xml
plonetheme/discovery/profiles/default/theme.xml
plonetheme/discovery/static/default.css
plonetheme/discovery/static/index.html
plonetheme/discovery/static/license.txt
plonetheme/discovery/static/manifest.cfg
plonetheme/discovery/static/rules.xml
plonetheme/discovery/static/images/img01.gif
plonetheme/discovery/static/images/img02.jpg
plonetheme/discovery/static/images/img03.jpg
plonetheme/discovery/static/images/img04.gif
plonetheme/discovery/static/images/img05.gif
plonetheme/discovery/static/images/img06.gif
plonetheme/discovery/static/images/img07.gif
plonetheme/discovery/static/images/img08.jpg
plonetheme/discovery/static/images/img09.gif