Metadata-Version: 1.0
Name: plonetheme.discovery
Version: 1.0
Summary: An installable Diazo theme for Plone 4.1
Home-page: http://svn.plone.org/svn/collective/plonetheme.discovery
Author: Giacomo Spettoli
Author-email: giacomo.spettoli@gmail.com
License: UNKNOWN
Platform: UNKNOWN
Classifier: Framework :: Plone
Classifier: Programming Language :: Python
